carbonify/__init__.py
carbonify/basecarbone.py
carbonify/utils.py
carbonify-0.1.1.dist-info/LICENSE
carbonify-0.1.1.dist-info/WHEEL
carbonify-0.1.1.dist-info/METADATA
carbonify-0.1.1.dist-info/RECORD
